Metadata-Version: 2.4
Name: proteinshake
Version: 0.3.16
Summary: Protein structure datasets for machine learning.
Home-page: https://proteinshake.readthedocs.io/en/latest/index.html
Author: Tim Kucera, Carlos Oliver, Dexiong Chen, Karsten Borgwardt
Author-email: kucera@biochem.mpg.de
Keywords: bioinformatics,deep-learning,computational-biology,macromolecular-structure
Classifier: Development Status :: 5 - Production/Stable
Classifier: License :: OSI Approved :: BSD License
Classifier: Programming Language :: Python
Classifier: Programming Language :: Python :: 3.7
Classifier: Programming Language :: Python :: 3.8
Classifier: Programming Language :: Python :: 3.9
Classifier: Programming Language :: Python :: 3.10
Classifier: Programming Language :: Python :: 3 :: Only
Requires-Python: >=3.7
License-File: LICENSE
Requires-Dist: biopandas>=0.4.1
Requires-Dist: pandas>=1.4.3
Requires-Dist: rdkit>=2024.9.6
Requires-Dist: tqdm>=4.64.0
Requires-Dist: scikit-learn>=1.1.1
Requires-Dist: joblib>=1.2.0
Requires-Dist: requests>=2.27.1
Requires-Dist: fastavro>=1.6.1
Requires-Dist: freesasa>=2.2.0.post3
Requires-Dist: goatools>=1.3.1
Dynamic: author
Dynamic: author-email
Dynamic: home-page
Dynamic: keywords
Dynamic: license-file
Dynamic: requires-dist
Dynamic: requires-python
Dynamic: summary
